py2many/__init__.py
py2many/__main__.py
py2many/analysis.py
py2many/annotation_transformer.py
py2many/ast_helpers.py
py2many/astx.py
py2many/cli.py
py2many/clike.py
py2many/context.py
py2many/declaration_extractor.py
py2many/exceptions.py
py2many/helpers.py
py2many/inference.py
py2many/language.py
py2many/mutability_transformer.py
py2many/nesting_transformer.py
py2many/process_helpers.py
py2many/python_transformer.py
py2many/registry.py
py2many/result.py
py2many/rewriters.py
py2many/scope.py
py2many/toposort_modules.py
py2many/tracer.py
py2many/pycpp/__init__.py
py2many/pycpp/clike.py
py2many/pycpp/plugins.py
py2many/pycpp/tracer.py
py2many/pycpp/transpiler.py
py2many/pyd/__init__.py
py2many/pyd/clike.py
py2many/pyd/plugins.py
py2many/pyd/transpiler.py
py2many/pydart/__init__.py
py2many/pydart/clike.py
py2many/pydart/plugins.py
py2many/pydart/transpiler.py
py2many/pygo/__init__.py
py2many/pygo/clike.py
py2many/pygo/inference.py
py2many/pygo/plugins.py
py2many/pygo/transpiler.py
py2many/pyjl/__init__.py
py2many/pyjl/clike.py
py2many/pyjl/inference.py
py2many/pyjl/plugins.py
py2many/pyjl/pyjl_vars.py
py2many/pyjl/rewriters.py
py2many/pyjl/transpiler.py
py2many/pykt/__init__.py
py2many/pykt/clike.py
py2many/pykt/inference.py
py2many/pykt/plugins.py
py2many/pykt/transpiler.py
py2many/pynim/__init__.py
py2many/pynim/clike.py
py2many/pynim/inference.py
py2many/pynim/plugins.py
py2many/pynim/transpiler.py
py2many/pyrs/__init__.py
py2many/pyrs/clike.py
py2many/pyrs/inference.py
py2many/pyrs/plugins.py
py2many/pyrs/transpiler.py
py2many/pysmt/__init__.py
py2many/pysmt/clike.py
py2many/pysmt/inference.py
py2many/pysmt/transpiler.py
py2many/pyv/__init__.py
py2many/pyv/clike.py
py2many/pyv/inference.py
py2many/pyv/plugins.py
py2many/pyv/transpiler.py
py2many-0.5.1.dist-info/LICENSE
py2many-0.5.1.dist-info/METADATA
py2many-0.5.1.dist-info/WHEEL
py2many-0.5.1.dist-info/entry_points.txt
py2many-0.5.1.dist-info/top_level.txt
py2many-0.5.1.dist-info/RECORD
