Metadata-Version: 2.1
Name: py2many
Version: 0.5.1
Summary: Python to CLike language transpiler.
Home-page: https://github.com/adsharma/py2many
Author: Arun Sharma
License: MIT
Classifier: License :: OSI Approved :: MIT License
Classifier: Operating System :: OS Independent
Classifier: Programming Language :: Python :: 3
Classifier: Topic :: Software Development
Classifier: Topic :: Utilities
Requires-Python: >=3.8
License-File: LICENSE
Requires-Dist: toposort
Requires-Dist: astor ; python_version < "3.9"
